{
  "type": "minecraft:block",
  "pools": [
    {
      "bonus_rolls": 0.0,
      "conditions": [
        {
          "condition": "minecraft:survives_explosion"
        },
        {
          "condition": "minecraft:block_state_property",
          "block": "createdeco:locked_zinc_door",
          "properties": {
            "half": "lower"
          }
        }
      ],
      "entries": [
        {
          "type": "minecraft:item",
          "name": "createdeco:locked_zinc_door"
        }
      ],
      "rolls": 1.0
    }
  ],
  "random_sequence": "createdeco:blocks/locked_zinc_door"
}
